[{"rightcounter": 182.04702758789062, "leftcounter": 316.0470275878906, "high": 1.00006103515625, "frequency": 498.09405517578125, "low": 1.0, "size": 6.103515625e-05}, {"rightcounter": 298.3118896484375, "leftcounter": 132.09405517578125, "high": 1.5, "frequency": 430.40594482421875, "low": 1.00006103515625, "size": 0.49993896484375}, {"rightcounter": 407.125, "leftcounter": 27.125, "high": 2.1015625, "frequency": 434.25, "low": 1.5, "size": 0.6015625}, {"rightcounter": 29.0, "leftcounter": 260.25, "high": 3.90625, "frequency": 289.25, "low": 2.1015625, "size": 1.8046875}, {"rightcounter": 153.75, "leftcounter": 213.75, "high": 5.8125, "frequency": 367.5, "low": 3.90625, "size": 1.90625}, {"rightcounter": 170, "leftcounter": 315.5, "high": 11.0, "frequency": 485.5, "low": 5.8125, "size": 5.1875}, {"rightcounter": 163.875, "leftcounter": 250.875, "high": 18.21875, "frequency": 414.75, "low": 11.0, "size": 7.21875}, {"rightcounter": 151.875, "leftcounter": 137.875, "high": 29.71875, "frequency": 289.75, "low": 18.21875, "size": 11.5}, {"rightcounter": 152, "leftcounter": 277.5, "high": 57.0, "frequency": 429.5, "low": 29.71875, "size": 27.28125}, {"rightcounter": 132.5, "leftcounter": 185.5, "high": 94.0, "frequency": 318.0, "low": 57.0, "size": 37.0}, {"rightcounter": 224.0, "leftcounter": 345.0, "high": 246.0, "frequency": 569.0, "low": 94.0, "size": 152.0}, {"rightcounter": 177.0, "leftcounter": 248.0, "high": 548.0, "frequency": 425.0, "low": 246.0, "size": 302.0}, {"rightcounter": 183.0, "leftcounter": 303.0, "high": 1536.1875, "frequency": 486.0, "low": 548.0, "size": 988.1875}, {"rightcounter": 166.625, "leftcounter": 292.625, "high": 4757.5390625, "frequency": 459.25, "low": 1536.1875, "size": 3221.3515625}, {"rightcounter": 158.5, "leftcounter": 337.25, "high": 17817.0, "frequency": 495.75, "low": 4757.5390625, "size": 13059.4609375}, {"rightcounter": 146.06640625, "leftcounter": 252.06640625, "high": 61133.5234375, "frequency": 398.1328125, "low": 17817.0, "size": 43316.5234375}, {"rightcounter": 155.06640625, "leftcounter": 329.06640625, "high": 334569.07763671875, "frequency": 484.1328125, "low": 61133.5234375, "size": 273435.55419921875}, {"rightcounter": 114.1875, "leftcounter": 249.796875, "high": 1403945.75, "frequency": 363.984375, "low": 334569.07763671875, "size": 1069376.6723632812}, {"rightcounter": 107.5, "leftcounter": 347.25, "high": 11106847.0, "frequency": 454.75, "low": 1403945.75, "size": 9702901.25}, {"rightcounter": 83.0, "leftcounter": 182.0, "high": 44373937.0, "frequency": 265.0, "low": 11106847.0, "size": 33267090.0}, {"rightcounter": 111.28125, "leftcounter": 303.28125, "high": 683472888.6875, "frequency": 414.5625, "low": 44373937.0, "size": 639098951.6875}, {"rightcounter": 63.5, "leftcounter": 371.9375, "high": 39875090050.0, "frequency": 435.4375, "low": 683472888.6875, "size": 39191617161.3125}, {"rightcounter": 156.75, "leftcounter": 156.75, "high": 4.423353473830059e+18, "frequency": 313.5, "low": 39875090050.0, "size": 4.423353433954969e+18}, {"rightcounter": 238.75, "leftcounter": 238.75, "high": 8.846706907785029e+18, "frequency": 477.5, "low": 4.423353473830059e+18, "size": 4.423353433954969e+18}, {"rightcounter": 1, "leftcounter": 0, "high": 8.896830189560866e+18, "frequency": 1, "low": 8.846706907785029e+18, "size": 5.012328177583718e+16}]