[{"high": 162.0, "merge": false, "frequency": 56386.666666666664, "low": 0.0, "size": 162.0}, {"high": 324.0, "merge": false, "frequency": 103231.66666666666, "low": 162.0, "size": 162.0}, {"high": 486.0, "merge": false, "frequency": 179209.66666666666, "low": 324.0, "size": 162.0}, {"high": 957.0, "merge": false, "frequency": 198156.0, "low": 486.0, "size": 471.0}, {"high": 1228.0, "merge": false, "frequency": 71372, "low": 957.0, "size": 271.0}, {"high": 1282.0, "merge": false, "frequency": 19180, "low": 1228.0, "size": 54.0}, {"high": 1295.0, "merge": false, "frequency": 2352, "low": 1282.0, "size": 13.0}, {"high": 1364.0, "merge": true, "frequency": 18564, "low": 1295.0, "size": 69.0}, {"high": 1940.0, "merge": false, "frequency": 166376, "low": 1364.0, "size": 576.0}, {"high": 2032.0, "merge": false, "frequency": 16576, "low": 1940.0, "size": 92.0}, {"high": 3270.0, "merge": false, "frequency": 169652, "low": 2032.0, "size": 1238.0}, {"high": 4095.0, "merge": false, "frequency": 55944, "low": 3270.0, "size": 825.0}, {"high": 4528.0, "merge": false, "frequency": 22372, "low": 4095.0, "size": 433.0}, {"high": 5450.0, "merge": false, "frequency": 41748, "low": 4528.0, "size": 922.0}, {"high": 9020.0, "merge": false, "frequency": 102228, "low": 5450.0, "size": 3570.0}, {"high": 11099.0, "merge": false, "frequency": 41468, "low": 9020.0, "size": 2079.0}, {"high": 11201.0, "merge": true, "frequency": 1260, "low": 11099.0, "size": 102.0}, {"high": 14983.0, "merge": false, "frequency": 44184, "low": 11201.0, "size": 3782.0}, {"high": 45076.0, "merge": false, "frequency": 80668, "low": 14983.0, "size": 30093.0}, {"high": 265996.0, "merge": false, "frequency": 9072, "low": 45076.0, "size": 220920.0}]