[{"high": 1.0, "frequency": 881.0, "low": 0.0, "size": 1.0}, {"high": 2.0, "frequency": 666.0, "low": 1.0, "size": 1.0}, {"high": 3.0, "frequency": 553.0, "low": 2.0, "size": 1.0}, {"high": 4.0, "frequency": 494.0, "low": 3.0, "size": 1.0}, {"high": 5.0, "frequency": 425.0, "low": 4.0, "size": 1.0}, {"high": 6.0, "frequency": 393.0, "low": 5.0, "size": 1.0}, {"high": 7.0, "frequency": 378.0, "low": 6.0, "size": 1.0}, {"high": 8.0, "frequency": 382.0, "low": 7.0, "size": 1.0}, {"high": 9.0, "frequency": 352.0, "low": 8.0, "size": 1.0}, {"high": 23.0, "frequency": 1632.0, "low": 9.0, "size": 14.0}, {"high": 24.0, "frequency": 253.0, "low": 23.0, "size": 1.0}, {"high": 38.0, "frequency": 1063.0, "low": 24.0, "size": 14.0}, {"high": 39.0, "frequency": 241.0, "low": 38.0, "size": 1.0}, {"high": 43.0, "frequency": 396.0, "low": 39.0, "size": 4.0}, {"high": 44.0, "frequency": 236.0, "low": 43.0, "size": 1.0}, {"high": 49.0, "frequency": 386.0, "low": 44.0, "size": 5.0}, {"high": 50.0, "frequency": 244.0, "low": 49.0, "size": 1.0}, {"high": 61.0, "frequency": 543.0, "low": 50.0, "size": 11.0}, {"high": 62.0, "frequency": 237.0, "low": 61.0, "size": 1.0}, {"high": 67.0, "frequency": 338.0, "low": 62.0, "size": 5.0}, {"high": 69.0, "frequency": 255.0, "low": 67.0, "size": 2.0}, {"high": 70.0, "frequency": 235.0, "low": 69.0, "size": 1.0}, {"high": 77.0, "frequency": 373.0, "low": 70.0, "size": 7.0}, {"high": 78.0, "frequency": 227.0, "low": 77.0, "size": 1.0}, {"high": 83.0, "frequency": 296.0, "low": 78.0, "size": 5.0}, {"high": 84.0, "frequency": 219.0, "low": 83.0, "size": 1.0}, {"high": 90.0, "frequency": 299.0, "low": 84.0, "size": 6.0}, {"high": 93.0, "frequency": 242.0, "low": 90.0, "size": 3.0}, {"high": 95.0, "frequency": 221.0, "low": 93.0, "size": 2.0}, {"high": 102.0, "frequency": 281.0, "low": 95.0, "size": 7.0}, {"high": 105.0, "frequency": 237.0, "low": 102.0, "size": 3.0}, {"high": 107.0, "frequency": 217.0, "low": 105.0, "size": 2.0}, {"high": 112.0, "frequency": 251.0, "low": 107.0, "size": 5.0}, {"high": 113.0, "frequency": 204.0, "low": 112.0, "size": 1.0}, {"high": 120.0, "frequency": 257.0, "low": 113.0, "size": 7.0}, {"high": 122.0, "frequency": 219.0, "low": 120.0, "size": 2.0}, {"high": 126.0, "frequency": 222.0, "low": 122.0, "size": 4.0}, {"high": 129.0, "frequency": 215.0, "low": 126.0, "size": 3.0}, {"high": 131.0, "frequency": 211.0, "low": 129.0, "size": 2.0}, {"high": 140.0, "frequency": 241.0, "low": 131.0, "size": 9.0}, {"high": 154.0, "frequency": 252.0, "low": 140.0, "size": 14.0}, {"high": 156.0, "frequency": 207.0, "low": 154.0, "size": 2.0}, {"high": 164.0, "frequency": 226.0, "low": 156.0, "size": 8.0}, {"high": 177.0, "frequency": 245.0, "low": 164.0, "size": 13.0}, {"high": 193.0, "frequency": 260.0, "low": 177.0, "size": 16.0}, {"high": 204.0, "frequency": 226.0, "low": 193.0, "size": 11.0}, {"high": 207.0, "frequency": 207.0, "low": 204.0, "size": 3.0}, {"high": 209.0, "frequency": 205.0, "low": 207.0, "size": 2.0}, {"high": 220.0, "frequency": 218.0, "low": 209.0, "size": 11.0}, {"high": 368.0, "frequency": 318.0, "low": 220.0, "size": 148.0}]