[{"rightcounter": 210.0, "leftcounter": 193, "high": 3.0, "frequency": 403.0, "low": 0.0, "size": 3.0}, {"rightcounter": 4.0, "leftcounter": 250.0, "high": 3.75, "frequency": 254.0, "low": 3.0, "size": 0.75}, {"rightcounter": 16.75, "leftcounter": 243.75, "high": 4.75, "frequency": 260.5, "low": 3.75, "size": 1.0}, {"rightcounter": 17.25, "leftcounter": 228.25, "high": 5.75, "frequency": 245.5, "low": 4.75, "size": 1.0}, {"rightcounter": 172.0, "leftcounter": 228.0, "high": 7.375, "frequency": 400.0, "low": 5.75, "size": 1.625}, {"rightcounter": 147.25, "leftcounter": 169.25, "high": 9.5625, "frequency": 316.5, "low": 7.375, "size": 2.1875}, {"rightcounter": 183.25, "leftcounter": 114.25, "high": 12.21875, "frequency": 297.5, "low": 9.5625, "size": 2.65625}, {"rightcounter": 227.0, "leftcounter": 165.0, "high": 17.765625, "frequency": 392.0, "low": 12.21875, "size": 5.546875}, {"rightcounter": 91.25, "leftcounter": 159.25, "high": 20.65625, "frequency": 250.5, "low": 17.765625, "size": 2.890625}, {"rightcounter": 104.25, "leftcounter": 135.25, "high": 23.94140625, "frequency": 239.5, "low": 20.65625, "size": 3.28515625}, {"rightcounter": 112.5, "leftcounter": 112.5, "high": 27.470703125, "frequency": 225.0, "low": 23.94140625, "size": 3.529296875}, {"rightcounter": 114.5, "leftcounter": 114.5, "high": 31.0, "frequency": 229, "low": 27.470703125, "size": 3.529296875}, {"rightcounter": 213.5, "leftcounter": 226.5, "high": 38.849609375, "frequency": 440.0, "low": 31.0, "size": 7.849609375}, {"rightcounter": 114.5, "leftcounter": 134.5, "high": 43.625, "frequency": 249.0, "low": 38.849609375, "size": 4.775390625}, {"rightcounter": 172.5, "leftcounter": 130.0, "high": 49.375, "frequency": 302.5, "low": 43.625, "size": 5.75}, {"rightcounter": 204.0, "leftcounter": 137.5, "high": 56.5, "frequency": 341.5, "low": 49.375, "size": 7.125}, {"rightcounter": 94.0, "leftcounter": 130.0, "high": 61.8046875, "frequency": 224.0, "low": 56.5, "size": 5.3046875}, {"rightcounter": 124.75, "leftcounter": 150.75, "high": 67.109375, "frequency": 275.5, "low": 61.8046875, "size": 5.3046875}, {"rightcounter": 111.25, "leftcounter": 106.25, "high": 72.5859375, "frequency": 217.5, "low": 67.109375, "size": 5.4765625}, {"rightcounter": 119.0, "leftcounter": 120.0, "high": 78.0625, "frequency": 239.0, "low": 72.5859375, "size": 5.4765625}, {"rightcounter": 123.0, "leftcounter": 143.0, "high": 84.5625, "frequency": 266.0, "low": 78.0625, "size": 6.5}, {"rightcounter": 168.5, "leftcounter": 130.5, "high": 91.0625, "frequency": 299.0, "low": 84.5625, "size": 6.5}, {"rightcounter": 159.0, "leftcounter": 130.0, "high": 98.0, "frequency": 289, "low": 91.0625, "size": 6.9375}, {"rightcounter": 195.5, "leftcounter": 185.5, "high": 105.875, "frequency": 381.0, "low": 98.0, "size": 7.875}, {"rightcounter": 85.0, "leftcounter": 138.0, "high": 110.5, "frequency": 223.0, "low": 105.875, "size": 4.625}, {"rightcounter": 153.75, "leftcounter": 127.75, "high": 116.5, "frequency": 281.5, "low": 110.5, "size": 6.0}, {"rightcounter": 162.0, "leftcounter": 166.5, "high": 124.25, "frequency": 328.5, "low": 116.5, "size": 7.75}, {"rightcounter": 86.5, "leftcounter": 127.5, "high": 129.96875, "frequency": 214.0, "low": 124.25, "size": 5.71875}, {"rightcounter": 188.0, "leftcounter": 228.0, "high": 141.0, "frequency": 416.0, "low": 129.96875, "size": 11.03125}, {"rightcounter": 165.0, "leftcounter": 209.0, "high": 149.5, "frequency": 374.0, "low": 141.0, "size": 8.5}, {"rightcounter": 167.5, "leftcounter": 157.5, "high": 158.0, "frequency": 325.0, "low": 149.5, "size": 8.5}, {"rightcounter": 147.0, "leftcounter": 153.0, "high": 166.0, "frequency": 300.0, "low": 158.0, "size": 8.0}, {"rightcounter": 131.0, "leftcounter": 185.0, "high": 174.5, "frequency": 316.0, "low": 166.0, "size": 8.5}, {"rightcounter": 114.5, "leftcounter": 121.5, "high": 181.0, "frequency": 236.0, "low": 174.5, "size": 6.5}, {"rightcounter": 111.5, "leftcounter": 110.5, "high": 187.5, "frequency": 222.0, "low": 181.0, "size": 6.5}, {"rightcounter": 140.5, "leftcounter": 205.5, "high": 198.75, "frequency": 346.0, "low": 187.5, "size": 11.25}, {"rightcounter": 172.5, "leftcounter": 182.5, "high": 210.875, "frequency": 355.0, "low": 198.75, "size": 12.125}, {"rightcounter": 154.5, "leftcounter": 129.5, "high": 220.671875, "frequency": 284.0, "low": 210.875, "size": 9.796875}, {"rightcounter": 188.0, "leftcounter": 244.0, "high": 237.0, "frequency": 432.0, "low": 220.671875, "size": 16.328125}, {"rightcounter": 158.5, "leftcounter": 165.5, "high": 251.0, "frequency": 324, "low": 237.0, "size": 14.0}, {"rightcounter": 129.5, "leftcounter": 163.5, "high": 264.3125, "frequency": 293.0, "low": 251.0, "size": 13.3125}, {"rightcounter": 109.125, "leftcounter": 118.125, "high": 277.625, "frequency": 227.25, "low": 264.3125, "size": 13.3125}, {"rightcounter": 144.125, "leftcounter": 184.125, "high": 300.64453125, "frequency": 328.25, "low": 277.625, "size": 23.01953125}, {"rightcounter": 147.625, "leftcounter": 162.625, "high": 325.392578125, "frequency": 310.25, "low": 300.64453125, "size": 24.748046875}, {"rightcounter": 143.625, "leftcounter": 136.625, "high": 350.140625, "frequency": 280.25, "low": 325.392578125, "size": 24.748046875}, {"rightcounter": 123.5, "leftcounter": 140.5, "high": 378.0, "frequency": 264.0, "low": 350.140625, "size": 27.859375}, {"rightcounter": 176.5, "leftcounter": 222.5, "high": 438.875, "frequency": 399.0, "low": 378.0, "size": 60.875}, {"rightcounter": 141.75, "leftcounter": 154.75, "high": 499.75, "frequency": 296.5, "low": 438.875, "size": 60.875}, {"rightcounter": 198.0, "leftcounter": 388.5, "high": 886.0, "frequency": 586.5, "low": 499.75, "size": 386.25}, {"rightcounter": 0, "leftcounter": 1, "high": 887.0, "frequency": 1, "low": 886.0, "size": 1.0}]