[{"high": 0.8, "merge": false, "frequency": 42.2, "low": 0.0, "size": 0.8}, {"high": 3.2, "merge": true, "frequency": 339.6, "low": 0.8, "size": 2.4000000000000004}, {"high": 4.0, "merge": false, "frequency": 38.2, "low": 3.2, "size": 0.7999999999999998}, {"high": 4.25, "merge": false, "frequency": 44.5, "low": 4.0, "size": 0.25}, {"high": 4.5, "merge": false, "frequency": 44.5, "low": 4.25, "size": 0.25}, {"high": 4.75, "merge": false, "frequency": 44.5, "low": 4.5, "size": 0.25}, {"high": 5.0, "merge": false, "frequency": 44.5, "low": 4.75, "size": 0.25}, {"high": 5.5, "merge": false, "frequency": 107.5, "low": 5.0, "size": 0.5}, {"high": 6.0, "merge": false, "frequency": 38.5, "low": 5.5, "size": 0.5}, {"high": 6.5, "merge": false, "frequency": 125.5, "low": 6.0, "size": 0.5}, {"high": 7.0, "merge": false, "frequency": 38.5, "low": 6.5, "size": 0.5}, {"high": 8.0, "merge": false, "frequency": 117, "low": 7.0, "size": 1.0}, {"high": 8.4, "merge": false, "frequency": 41.4, "low": 8.0, "size": 0.40000000000000036}, {"high": 8.8, "merge": false, "frequency": 41.4, "low": 8.4, "size": 0.40000000000000036}, {"high": 9.200000000000001, "merge": false, "frequency": 41.4, "low": 8.8, "size": 0.40000000000000036}, {"high": 9.600000000000001, "merge": false, "frequency": 41.4, "low": 9.200000000000001, "size": 0.40000000000000036}, {"high": 10.000000000000002, "merge": false, "frequency": 41.4, "low": 9.600000000000001, "size": 0.40000000000000036}, {"high": 12.0, "merge": true, "frequency": 158, "low": 10.0, "size": 2.0}, {"high": 17.0, "merge": true, "frequency": 259.0, "low": 12.0, "size": 5.0}, {"high": 18.0, "merge": false, "frequency": 50.0, "low": 17.0, "size": 1.0}, {"high": 19.0, "merge": false, "frequency": 50.0, "low": 18.0, "size": 1.0}, {"high": 20.0, "merge": false, "frequency": 50.0, "low": 19.0, "size": 1.0}, {"high": 24.0, "merge": true, "frequency": 214, "low": 20.0, "size": 4.0}, {"high": 30.0, "merge": true, "frequency": 260.0, "low": 24.0, "size": 6.0}, {"high": 31.0, "merge": false, "frequency": 47, "low": 30.0, "size": 1.0}, {"high": 37.0, "merge": true, "frequency": 232, "low": 31.0, "size": 6.0}, {"high": 39.0, "merge": false, "frequency": 71, "low": 37.0, "size": 2.0}, {"high": 40.0, "merge": false, "frequency": 40, "low": 39.0, "size": 1.0}, {"high": 44.0, "merge": true, "frequency": 141, "low": 40.0, "size": 4.0}, {"high": 52.0, "merge": true, "frequency": 284.0, "low": 44.0, "size": 8.0}, {"high": 54.0, "merge": false, "frequency": 63, "low": 52.0, "size": 2.0}, {"high": 58.0, "merge": true, "frequency": 122, "low": 54.0, "size": 4.0}, {"high": 61.0, "merge": false, "frequency": 87, "low": 58.0, "size": 3.0}, {"high": 62.0, "merge": false, "frequency": 34, "low": 61.0, "size": 1.0}, {"high": 72.0, "merge": true, "frequency": 294, "low": 62.0, "size": 10.0}, {"high": 75.0, "merge": false, "frequency": 83, "low": 72.0, "size": 3.0}, {"high": 83.80000000000001, "merge": true, "frequency": 248.39999999999998, "low": 75.0, "size": 8.800000000000011}, {"high": 86.00000000000001, "merge": false, "frequency": 84.6, "low": 83.80000000000001, "size": 2.200000000000003}, {"high": 87.66666666666667, "merge": false, "frequency": 45.0, "low": 86.0, "size": 1.6666666666666714}, {"high": 89.33333333333334, "merge": false, "frequency": 45.0, "low": 87.66666666666667, "size": 1.6666666666666714}, {"high": 91.00000000000001, "merge": false, "frequency": 45.0, "low": 89.33333333333334, "size": 1.6666666666666714}, {"high": 93.33333333333333, "merge": false, "frequency": 86.33333333333334, "low": 91.0, "size": 2.3333333333333286}, {"high": 97.99999999999999, "merge": true, "frequency": 128.66666666666669, "low": 93.33333333333333, "size": 4.666666666666657}, {"high": 99.0, "merge": false, "frequency": 29, "low": 98.0, "size": 1.0}, {"high": 105.0, "merge": true, "frequency": 203, "low": 99.0, "size": 6.0}, {"high": 106.66666666666667, "merge": false, "frequency": 47.333333333333336, "low": 105.0, "size": 1.6666666666666714}, {"high": 108.33333333333334, "merge": false, "frequency": 47.333333333333336, "low": 106.66666666666667, "size": 1.6666666666666714}, {"high": 110.00000000000001, "merge": false, "frequency": 47.333333333333336, "low": 108.33333333333334, "size": 1.6666666666666714}, {"high": 116.0, "merge": true, "frequency": 193.0, "low": 110.0, "size": 6.0}, {"high": 124.0, "merge": true, "frequency": 227, "low": 116.0, "size": 8.0}, {"high": 128.0, "merge": true, "frequency": 110, "low": 124.0, "size": 4.0}, {"high": 137.0, "merge": true, "frequency": 227.0, "low": 128.0, "size": 9.0}, {"high": 138.66666666666666, "merge": false, "frequency": 43.0, "low": 137.0, "size": 1.6666666666666572}, {"high": 140.33333333333331, "merge": false, "frequency": 43.0, "low": 138.66666666666666, "size": 1.6666666666666572}, {"high": 141.99999999999997, "merge": false, "frequency": 43.0, "low": 140.33333333333331, "size": 1.6666666666666572}, {"high": 144.0, "merge": true, "frequency": 57, "low": 142.0, "size": 2.0}, {"high": 145.4, "merge": false, "frequency": 36.0, "low": 144.0, "size": 1.4000000000000057}, {"high": 146.8, "merge": false, "frequency": 36.0, "low": 145.4, "size": 1.4000000000000057}, {"high": 148.20000000000002, "merge": false, "frequency": 36.0, "low": 146.8, "size": 1.4000000000000057}, {"high": 149.60000000000002, "merge": false, "frequency": 36.0, "low": 148.20000000000002, "size": 1.4000000000000057}, {"high": 151.00000000000003, "merge": false, "frequency": 36.0, "low": 149.60000000000002, "size": 1.4000000000000057}, {"high": 154.0, "merge": false, "frequency": 81, "low": 151.0, "size": 3.0}, {"high": 155.0, "merge": false, "frequency": 26, "low": 154.0, "size": 1.0}, {"high": 159.0, "merge": false, "frequency": 113, "low": 155.0, "size": 4.0}, {"high": 166.0, "merge": true, "frequency": 185, "low": 159.0, "size": 7.0}, {"high": 168.0, "merge": true, "frequency": 37, "low": 166.0, "size": 2.0}, {"high": 169.4, "merge": false, "frequency": 37.0, "low": 168.0, "size": 1.4000000000000057}, {"high": 170.8, "merge": false, "frequency": 37.0, "low": 169.4, "size": 1.4000000000000057}, {"high": 172.20000000000002, "merge": false, "frequency": 37.0, "low": 170.8, "size": 1.4000000000000057}, {"high": 173.60000000000002, "merge": false, "frequency": 37.0, "low": 172.20000000000002, "size": 1.4000000000000057}, {"high": 175.00000000000003, "merge": false, "frequency": 37.0, "low": 173.60000000000002, "size": 1.4000000000000057}, {"high": 177.0, "merge": false, "frequency": 54, "low": 175.0, "size": 2.0}, {"high": 187.0, "merge": true, "frequency": 228, "low": 177.0, "size": 10.0}, {"high": 195.0, "merge": true, "frequency": 176, "low": 187.0, "size": 8.0}, {"high": 214.0, "merge": true, "frequency": 365, "low": 195.0, "size": 19.0}, {"high": 220.0, "merge": false, "frequency": 104, "low": 214.0, "size": 6.0}, {"high": 223.0, "merge": true, "frequency": 56, "low": 220.0, "size": 3.0}, {"high": 225.33333333333334, "merge": false, "frequency": 42.0, "low": 223.0, "size": 2.333333333333343}, {"high": 227.66666666666669, "merge": false, "frequency": 42.0, "low": 225.33333333333334, "size": 2.333333333333343}, {"high": 230.00000000000003, "merge": false, "frequency": 42.0, "low": 227.66666666666669, "size": 2.333333333333343}, {"high": 252.0, "merge": true, "frequency": 323, "low": 230.0, "size": 22.0}, {"high": 259.0, "merge": true, "frequency": 119, "low": 252.0, "size": 7.0}, {"high": 260.0, "merge": false, "frequency": 11, "low": 259.0, "size": 1.0}, {"high": 267.0, "merge": true, "frequency": 88, "low": 260.0, "size": 7.0}, {"high": 280.0, "merge": true, "frequency": 153, "low": 267.0, "size": 13.0}, {"high": 282.0, "merge": false, "frequency": 21, "low": 280.0, "size": 2.0}, {"high": 286.0, "merge": false, "frequency": 42.0, "low": 282.0, "size": 4.0}, {"high": 290.0, "merge": false, "frequency": 42.0, "low": 286.0, "size": 4.0}, {"high": 294.0, "merge": false, "frequency": 42.0, "low": 290.0, "size": 4.0}, {"high": 358.0000000000001, "merge": true, "frequency": 510.9999999999999, "low": 294.0, "size": 64.00000000000011}, {"high": 367.0, "merge": true, "frequency": 55, "low": 358.0, "size": 9.0}, {"high": 382.0, "merge": false, "frequency": 89, "low": 367.0, "size": 15.0}, {"high": 393.0, "merge": false, "frequency": 43, "low": 382.0, "size": 11.0}, {"high": 457.0, "merge": true, "frequency": 243, "low": 393.0, "size": 64.0}, {"high": 493.0, "merge": true, "frequency": 131, "low": 457.0, "size": 36.0}, {"high": 532.0, "merge": false, "frequency": 82, "low": 493.0, "size": 39.0}, {"high": 533.0, "merge": false, "frequency": 3, "low": 532.0, "size": 1.0}, {"high": 615.0, "merge": true, "frequency": 111, "low": 533.0, "size": 82.0}, {"high": 760.0, "merge": false, "frequency": 164, "low": 615.0, "size": 145.0}, {"high": 887.0, "merge": false, "frequency": 40, "low": 760.0, "size": 127.0}]