[{"rightcounter": 0, "leftcounter": 4, "high": 2.0, "frequency": 4, "low": 1.0, "size": 1.0}, {"rightcounter": 0, "leftcounter": 1, "high": 3.0, "frequency": 1, "low": 2.0, "size": 1.0}, {"rightcounter": 0, "leftcounter": 1, "high": 7.0, "frequency": 1, "low": 3.0, "size": 4.0}, {"rightcounter": 0, "leftcounter": 1, "high": 9.0, "frequency": 1, "low": 7.0, "size": 2.0}, {"rightcounter": 0, "leftcounter": 1, "high": 11.0, "frequency": 1, "low": 9.0, "size": 2.0}, {"rightcounter": 0, "leftcounter": 1, "high": 29.0, "frequency": 1, "low": 11.0, "size": 18.0}, {"rightcounter": 0, "leftcounter": 1, "high": 48.0, "frequency": 1, "low": 29.0, "size": 19.0}, {"rightcounter": 0, "leftcounter": 1, "high": 51.0, "frequency": 1, "low": 48.0, "size": 3.0}, {"rightcounter": 0, "leftcounter": 1, "high": 127.0, "frequency": 1, "low": 51.0, "size": 76.0}, {"rightcounter": 0, "leftcounter": 1, "high": 373.0, "frequency": 1, "low": 127.0, "size": 246.0}, {"rightcounter": 0, "leftcounter": 1, "high": 1933.0, "frequency": 1, "low": 373.0, "size": 1560.0}, {"rightcounter": 0, "leftcounter": 1, "high": 3230.0, "frequency": 1, "low": 1933.0, "size": 1297.0}, {"rightcounter": 0, "leftcounter": 1, "high": 16430.0, "frequency": 1, "low": 3230.0, "size": 13200.0}, {"rightcounter": 0, "leftcounter": 1, "high": 20208.0, "frequency": 1, "low": 16430.0, "size": 3778.0}, {"rightcounter": 0, "leftcounter": 1, "high": 20542.0, "frequency": 1, "low": 20208.0, "size": 334.0}, {"rightcounter": 0, "leftcounter": 1, "high": 49946.0, "frequency": 1, "low": 20542.0, "size": 29404.0}, {"rightcounter": 0, "leftcounter": 1, "high": 98653.0, "frequency": 1, "low": 49946.0, "size": 48707.0}, {"rightcounter": 0, "leftcounter": 1, "high": 333814.0, "frequency": 1, "low": 98653.0, "size": 235161.0}, {"rightcounter": 0, "leftcounter": 1, "high": 663922.0, "frequency": 1, "low": 333814.0, "size": 330108.0}, {"rightcounter": 0, "leftcounter": 1, "high": 10090444.0, "frequency": 1, "low": 663922.0, "size": 9426522.0}, {"rightcounter": 0, "leftcounter": 1, "high": 22451401.0, "frequency": 1, "low": 10090444.0, "size": 12360957.0}, {"rightcounter": 0, "leftcounter": 1, "high": 35399026.0, "frequency": 1, "low": 22451401.0, "size": 12947625.0}, {"rightcounter": 0, "leftcounter": 1, "high": 37982092.0, "frequency": 1, "low": 35399026.0, "size": 2583066.0}, {"rightcounter": 0, "leftcounter": 1, "high": 17644977098.0, "frequency": 1, "low": 37982092.0, "size": 17606995006.0}, {"rightcounter": 0, "leftcounter": 1, "high": 17644977099.0, "frequency": 1, "low": 17644977098.0, "size": 1.0}]