[{"rightcounter": 462.0, "leftcounter": 358.0, "high": 5.0, "frequency": 820.0, "low": 1.0, "size": 4.0}, {"rightcounter": 542.0, "leftcounter": 1000.0, "high": 14.0, "frequency": 1542.0, "low": 5.0, "size": 9.0}, {"rightcounter": 921.0, "leftcounter": 1092.0, "high": 40.66796875, "frequency": 2013.0, "low": 14.0, "size": 26.66796875}, {"rightcounter": 699.0, "leftcounter": 817.0, "high": 73.0, "frequency": 1516.0, "low": 40.66796875, "size": 32.33203125}, {"rightcounter": 468.0, "leftcounter": 468.0, "high": 99.34375, "frequency": 936.0, "low": 73.0, "size": 26.34375}, {"rightcounter": 604.0, "leftcounter": 604.0, "high": 125.6875, "frequency": 1208.0, "low": 99.34375, "size": 26.34375}, {"rightcounter": 657.75, "leftcounter": 678.75, "high": 164.9873046875, "frequency": 1336.5, "low": 125.6875, "size": 39.2998046875}, {"rightcounter": 640.75, "leftcounter": 687.75, "high": 204.287109375, "frequency": 1328.5, "low": 164.9873046875, "size": 39.2998046875}, {"rightcounter": 938.25, "leftcounter": 1164.25, "high": 282.88671875, "frequency": 2102.5, "low": 204.287109375, "size": 78.599609375}, {"rightcounter": 639.0625, "leftcounter": 756.0625, "high": 414.9150390625, "frequency": 1395.125, "low": 282.88671875, "size": 132.0283203125}, {"rightcounter": 1832.25, "leftcounter": 1347.125, "high": 971.0, "frequency": 3179.375, "low": 414.9150390625, "size": 556.0849609375}, {"rightcounter": 2, "leftcounter": 0, "high": 978.0, "frequency": 2, "low": 971.0, "size": 7.0}]