[{"rightcounter": 54759.8984375, "leftcounter": 128388.8984375, "high": 1.015625, "frequency": 183148.796875, "low": 1.0, "size": 0.015625}, {"rightcounter": 135140.40625, "leftcounter": 46975.796875, "high": 3.25, "frequency": 182116.203125, "low": 1.015625, "size": 2.234375}, {"rightcounter": 52431.0, "leftcounter": 62304.0, "high": 6.0, "frequency": 114735.0, "low": 3.25, "size": 2.75}, {"rightcounter": 79336.5, "leftcounter": 94263.5, "high": 9.375, "frequency": 173600.0, "low": 6.0, "size": 3.375}, {"rightcounter": 58128.234375, "leftcounter": 91626.234375, "high": 27.28125, "frequency": 149754.46875, "low": 9.375, "size": 17.90625}, {"rightcounter": 114935.0625, "leftcounter": 81690.46875, "high": 81.0, "frequency": 196625.53125, "low": 27.28125, "size": 53.71875}, {"rightcounter": 0, "leftcounter": 20, "high": 82.0, "frequency": 20, "low": 81.0, "size": 1.0}]