[{"high": 1.0, "frequency": 32, "low": 0.0, "size": 1.0}, {"high": 2.0, "frequency": 15984, "low": 1.0, "size": 1.0}, {"high": 3.0, "frequency": 14240, "low": 2.0, "size": 1.0}, {"high": 4.0, "frequency": 12480, "low": 3.0, "size": 1.0}, {"high": 5.0, "frequency": 11744, "low": 4.0, "size": 1.0}, {"high": 6.0, "frequency": 10928, "low": 5.0, "size": 1.0}, {"high": 7.0, "frequency": 10496, "low": 6.0, "size": 1.0}, {"high": 8.0, "frequency": 10144, "low": 7.0, "size": 1.0}, {"high": 9.0, "frequency": 9872, "low": 8.0, "size": 1.0}, {"high": 10.0, "frequency": 9472, "low": 9.0, "size": 1.0}, {"high": 11.0, "frequency": 9184, "low": 10.0, "size": 1.0}, {"high": 12.0, "frequency": 8864, "low": 11.0, "size": 1.0}, {"high": 13.0, "frequency": 8592, "low": 12.0, "size": 1.0}, {"high": 14.0, "frequency": 8272, "low": 13.0, "size": 1.0}, {"high": 15.0, "frequency": 8064, "low": 14.0, "size": 1.0}, {"high": 16.0, "frequency": 7856, "low": 15.0, "size": 1.0}, {"high": 17.0, "frequency": 7584, "low": 16.0, "size": 1.0}, {"high": 18.0, "frequency": 7264, "low": 17.0, "size": 1.0}, {"high": 19.0, "frequency": 7104, "low": 18.0, "size": 1.0}, {"high": 20.0, "frequency": 6880, "low": 19.0, "size": 1.0}, {"high": 21.0, "frequency": 6768, "low": 20.0, "size": 1.0}, {"high": 22.0, "frequency": 6560, "low": 21.0, "size": 1.0}, {"high": 23.0, "frequency": 6544, "low": 22.0, "size": 1.0}, {"high": 24.0, "frequency": 6352, "low": 23.0, "size": 1.0}, {"high": 25.0, "frequency": 6272, "low": 24.0, "size": 1.0}, {"high": 26.0, "frequency": 6032, "low": 25.0, "size": 1.0}, {"high": 27.0, "frequency": 5888, "low": 26.0, "size": 1.0}, {"high": 28.0, "frequency": 5744, "low": 27.0, "size": 1.0}, {"high": 29.0, "frequency": 5584, "low": 28.0, "size": 1.0}, {"high": 30.0, "frequency": 5408, "low": 29.0, "size": 1.0}, {"high": 31.0, "frequency": 5360, "low": 30.0, "size": 1.0}, {"high": 32.0, "frequency": 5072, "low": 31.0, "size": 1.0}, {"high": 33.0, "frequency": 5072, "low": 32.0, "size": 1.0}, {"high": 34.0, "frequency": 4832, "low": 33.0, "size": 1.0}, {"high": 35.0, "frequency": 4720, "low": 34.0, "size": 1.0}, {"high": 36.0, "frequency": 4544, "low": 35.0, "size": 1.0}, {"high": 37.0, "frequency": 4432, "low": 36.0, "size": 1.0}, {"high": 38.0, "frequency": 4224, "low": 37.0, "size": 1.0}, {"high": 39.0, "frequency": 4208, "low": 38.0, "size": 1.0}, {"high": 40.0, "frequency": 4176, "low": 39.0, "size": 1.0}, {"high": 41.0, "frequency": 4064, "low": 40.0, "size": 1.0}, {"high": 42.0, "frequency": 3936, "low": 41.0, "size": 1.0}, {"high": 43.0, "frequency": 3920, "low": 42.0, "size": 1.0}, {"high": 44.0, "frequency": 3824, "low": 43.0, "size": 1.0}, {"high": 45.0, "frequency": 3776, "low": 44.0, "size": 1.0}, {"high": 46.0, "frequency": 3600, "low": 45.0, "size": 1.0}, {"high": 47.0, "frequency": 3488, "low": 46.0, "size": 1.0}, {"high": 48.0, "frequency": 3424, "low": 47.0, "size": 1.0}, {"high": 49.0, "frequency": 3392, "low": 48.0, "size": 1.0}, {"high": 256.0, "frequency": 473728, "low": 49.0, "size": 207.0}]