[{"high": 2.0, "frequency": 32225.6, "low": 1.0, "size": 1.0}, {"high": 3.0, "frequency": 28949.6, "low": 2.0, "size": 1.0}, {"high": 4.0, "frequency": 28236.6, "low": 3.0, "size": 1.0}, {"high": 5.0, "frequency": 27625.59999999999, "low": 4.0, "size": 1.0}, {"high": 6.0, "frequency": 27098.600000000006, "low": 5.0, "size": 1.0}, {"high": 7.0, "frequency": 26874.600000000006, "low": 6.0, "size": 1.0}, {"high": 8.0, "frequency": 26685.599999999977, "low": 7.0, "size": 1.0}, {"high": 10.0, "frequency": 28698.600000000006, "low": 8.0, "size": 2.0}, {"high": 12.0, "frequency": 28071.600000000006, "low": 10.0, "size": 2.0}, {"high": 81.0, "frequency": 45533.600000000006, "low": 12.0, "size": 69.0}]