[{"high": 25789.333333333336, "merge": true, "frequency": 527.0, "low": 12285.0, "size": 13504.333333333336}, {"high": 39161.25, "merge": true, "frequency": 1085.0, "low": 25789.333333333336, "size": 13371.916666666664}, {"high": 40816.1875, "merge": false, "frequency": 134.75, "low": 39161.25, "size": 1654.9375}, {"high": 42471.125, "merge": false, "frequency": 134.75, "low": 40816.1875, "size": 1654.9375}, {"high": 44126.0625, "merge": false, "frequency": 134.75, "low": 42471.125, "size": 1654.9375}, {"high": 45781.0, "merge": false, "frequency": 134.75, "low": 44126.0625, "size": 1654.9375}, {"high": 76845.0, "merge": true, "frequency": 2031, "low": 45781.0, "size": 31064.0}, {"high": 77516.0, "merge": false, "frequency": 54, "low": 76845.0, "size": 671.0}, {"high": 80413.5, "merge": false, "frequency": 202.5, "low": 77516.0, "size": 2897.5}, {"high": 83311.0, "merge": false, "frequency": 202.5, "low": 80413.5, "size": 2897.5}, {"high": 84154.0, "merge": false, "frequency": 79, "low": 83311.0, "size": 843.0}, {"high": 86330.0, "merge": false, "frequency": 148.5, "low": 84154.0, "size": 2176.0}, {"high": 88506.0, "merge": false, "frequency": 148.5, "low": 86330.0, "size": 2176.0}, {"high": 101603.0, "merge": true, "frequency": 1303.0, "low": 88506.0, "size": 13097.0}, {"high": 109015.0, "merge": true, "frequency": 1076.0, "low": 101603.0, "size": 7412.0}, {"high": 117037.0, "merge": true, "frequency": 1223.0, "low": 109015.0, "size": 8022.0}, {"high": 121772.0, "merge": true, "frequency": 745.0, "low": 117037.0, "size": 4735.0}, {"high": 122272.0, "merge": false, "frequency": 76, "low": 121772.0, "size": 500.0}, {"high": 128354.0, "merge": true, "frequency": 781.0, "low": 122272.0, "size": 6082.0}, {"high": 141297.0, "merge": true, "frequency": 1479.0, "low": 128354.0, "size": 12943.0}, {"high": 142318.33333333334, "merge": false, "frequency": 142.66666666666666, "low": 141297.0, "size": 1021.333333333343}, {"high": 143339.6666666667, "merge": false, "frequency": 142.66666666666666, "low": 142318.33333333334, "size": 1021.333333333343}, {"high": 144361.00000000003, "merge": false, "frequency": 142.66666666666666, "low": 143339.6666666667, "size": 1021.333333333343}, {"high": 159449.0, "merge": true, "frequency": 1984.0, "low": 144361.0, "size": 15088.0}, {"high": 160187.0, "merge": false, "frequency": 141, "low": 159449.0, "size": 738.0}, {"high": 168294.00000000003, "merge": true, "frequency": 1302.0, "low": 160187.0, "size": 8107.000000000029}, {"high": 176756.0, "merge": true, "frequency": 1622, "low": 168294.0, "size": 8462.0}, {"high": 180211.0, "merge": true, "frequency": 619.0, "low": 176756.0, "size": 3455.0}, {"high": 186824.00000000003, "merge": true, "frequency": 1248.0, "low": 180211.0, "size": 6613.000000000029}, {"high": 190709.0, "merge": true, "frequency": 844.0, "low": 186824.0, "size": 3885.0}, {"high": 193366.0, "merge": true, "frequency": 562.0, "low": 190709.0, "size": 2657.0}, {"high": 193524.0, "merge": false, "frequency": 31, "low": 193366.0, "size": 158.0}, {"high": 197200.0, "merge": true, "frequency": 658.0, "low": 193524.0, "size": 3676.0}, {"high": 215646.0, "merge": true, "frequency": 2898, "low": 197200.0, "size": 18446.0}, {"high": 216851.0, "merge": false, "frequency": 158, "low": 215646.0, "size": 1205.0}, {"high": 234720.99999999997, "merge": true, "frequency": 1822.0, "low": 216851.0, "size": 17869.99999999997}, {"high": 245487.0, "merge": true, "frequency": 994.0, "low": 234721.0, "size": 10766.0}, {"high": 265477.0, "merge": true, "frequency": 1341.0, "low": 245487.0, "size": 19990.0}, {"high": 266015.0, "merge": false, "frequency": 26, "low": 265477.0, "size": 538.0}, {"high": 268740.5, "merge": false, "frequency": 175.5, "low": 266015.0, "size": 2725.5}, {"high": 271466.0, "merge": false, "frequency": 175.5, "low": 268740.5, "size": 2725.5}, {"high": 289980.0, "merge": true, "frequency": 1080, "low": 271466.0, "size": 18514.0}, {"high": 292175.0, "merge": false, "frequency": 117, "low": 289980.0, "size": 2195.0}, {"high": 311512.0, "merge": true, "frequency": 877, "low": 292175.0, "size": 19337.0}, {"high": 337895.0, "merge": true, "frequency": 1078.0, "low": 311512.0, "size": 26383.0}, {"high": 338409.0, "merge": false, "frequency": 29, "low": 337895.0, "size": 514.0}, {"high": 427251.6666666667, "merge": true, "frequency": 2034.6666666666665, "low": 338409.0, "size": 88842.66666666669}, {"high": 507875.00000000006, "merge": true, "frequency": 693.3333333333333, "low": 427251.6666666667, "size": 80623.33333333337}, {"high": 544091.0, "merge": false, "frequency": 105, "low": 507875.0, "size": 36216.0}, {"high": 1484706.0, "merge": false, "frequency": 257, "low": 544091.0, "size": 940615.0}]