[{"high": 6.0, "frequency": 3.03, "low": 0.0, "size": 6.0}, {"high": 7.0, "frequency": 3.03, "low": 6.0, "size": 1.0}, {"high": 10.0, "frequency": 3.03, "low": 7.0, "size": 3.0}, {"high": 11.0, "frequency": 3.03, "low": 10.0, "size": 1.0}, {"high": 13.0, "frequency": 3.03, "low": 11.0, "size": 2.0}, {"high": 14.0, "frequency": 3.03, "low": 13.0, "size": 1.0}, {"high": 17.0, "frequency": 3.03, "low": 14.0, "size": 3.0}, {"high": 18.0, "frequency": 3.03, "low": 17.0, "size": 1.0}, {"high": 20.0, "frequency": 3.03, "low": 18.0, "size": 2.0}, {"high": 23.0, "frequency": 3.03, "low": 20.0, "size": 3.0}, {"high": 24.0, "frequency": 3.03, "low": 23.0, "size": 1.0}, {"high": 28.0, "frequency": 3.03, "low": 24.0, "size": 4.0}, {"high": 31.0, "frequency": 3.03, "low": 28.0, "size": 3.0}, {"high": 35.0, "frequency": 3.03, "low": 31.0, "size": 4.0}, {"high": 40.0, "frequency": 3.03, "low": 35.0, "size": 5.0}, {"high": 42.0, "frequency": 3.03, "low": 40.0, "size": 2.0}, {"high": 46.0, "frequency": 3.03, "low": 42.0, "size": 4.0}, {"high": 53.0, "frequency": 3.03, "low": 46.0, "size": 7.0}, {"high": 54.0, "frequency": 3.03, "low": 53.0, "size": 1.0}, {"high": 56.0, "frequency": 3.03, "low": 54.0, "size": 2.0}, {"high": 59.0, "frequency": 3.03, "low": 56.0, "size": 3.0}, {"high": 65.0, "frequency": 3.03, "low": 59.0, "size": 6.0}, {"high": 68.0, "frequency": 3.03, "low": 65.0, "size": 3.0}, {"high": 71.0, "frequency": 3.03, "low": 68.0, "size": 3.0}, {"high": 74.0, "frequency": 3.03, "low": 71.0, "size": 3.0}, {"high": 76.0, "frequency": 3.03, "low": 74.0, "size": 2.0}, {"high": 81.0, "frequency": 3.03, "low": 76.0, "size": 5.0}, {"high": 82.0, "frequency": 3.03, "low": 81.0, "size": 1.0}, {"high": 89.0, "frequency": 3.03, "low": 82.0, "size": 7.0}, {"high": 90.0, "frequency": 3.03, "low": 89.0, "size": 1.0}, {"high": 101.0, "frequency": 3.03, "low": 90.0, "size": 11.0}, {"high": 102.0, "frequency": 3.03, "low": 101.0, "size": 1.0}, {"high": 107.0, "frequency": 3.03, "low": 102.0, "size": 5.0}, {"high": 108.0, "frequency": 3.03, "low": 107.0, "size": 1.0}, {"high": 110.0, "frequency": 3.03, "low": 108.0, "size": 2.0}, {"high": 111.0, "frequency": 3.03, "low": 110.0, "size": 1.0}, {"high": 127.0, "frequency": 3.03, "low": 111.0, "size": 16.0}, {"high": 128.0, "frequency": 3.03, "low": 127.0, "size": 1.0}, {"high": 130.0, "frequency": 3.03, "low": 128.0, "size": 2.0}, {"high": 136.0, "frequency": 3.03, "low": 130.0, "size": 6.0}, {"high": 137.0, "frequency": 3.03, "low": 136.0, "size": 1.0}, {"high": 140.0, "frequency": 3.03, "low": 137.0, "size": 3.0}, {"high": 141.0, "frequency": 3.03, "low": 140.0, "size": 1.0}, {"high": 146.0, "frequency": 3.03, "low": 141.0, "size": 5.0}, {"high": 151.0, "frequency": 3.03, "low": 146.0, "size": 5.0}, {"high": 154.0, "frequency": 3.03, "low": 151.0, "size": 3.0}, {"high": 159.0, "frequency": 3.03, "low": 154.0, "size": 5.0}, {"high": 161.0, "frequency": 3.03, "low": 159.0, "size": 2.0}, {"high": 162.0, "frequency": 3.03, "low": 161.0, "size": 1.0}, {"high": 166.0, "frequency": 3.03, "low": 162.0, "size": 4.0}, {"high": 167.0, "frequency": 3.03, "low": 166.0, "size": 1.0}, {"high": 170.0, "frequency": 3.03, "low": 167.0, "size": 3.0}, {"high": 173.0, "frequency": 3.03, "low": 170.0, "size": 3.0}, {"high": 177.0, "frequency": 3.03, "low": 173.0, "size": 4.0}, {"high": 186.0, "frequency": 3.03, "low": 177.0, "size": 9.0}, {"high": 187.0, "frequency": 3.03, "low": 186.0, "size": 1.0}, {"high": 199.0, "frequency": 3.03, "low": 187.0, "size": 12.0}, {"high": 200.0, "frequency": 3.03, "low": 199.0, "size": 1.0}, {"high": 207.0, "frequency": 3.03, "low": 200.0, "size": 7.0}, {"high": 214.0, "frequency": 3.03, "low": 207.0, "size": 7.0}, {"high": 215.0, "frequency": 3.03, "low": 214.0, "size": 1.0}, {"high": 232.0, "frequency": 3.03, "low": 215.0, "size": 17.0}, {"high": 233.0, "frequency": 3.03, "low": 232.0, "size": 1.0}, {"high": 238.0, "frequency": 3.03, "low": 233.0, "size": 5.0}, {"high": 244.0, "frequency": 3.03, "low": 238.0, "size": 6.0}, {"high": 245.0, "frequency": 3.03, "low": 244.0, "size": 1.0}, {"high": 257.0, "frequency": 3.03, "low": 245.0, "size": 12.0}, {"high": 258.0, "frequency": 3.03, "low": 257.0, "size": 1.0}, {"high": 264.0, "frequency": 3.03, "low": 258.0, "size": 6.0}, {"high": 277.0, "frequency": 3.03, "low": 264.0, "size": 13.0}, {"high": 296.0, "frequency": 3.03, "low": 277.0, "size": 19.0}, {"high": 304.0, "frequency": 3.03, "low": 296.0, "size": 8.0}, {"high": 310.0, "frequency": 3.03, "low": 304.0, "size": 6.0}, {"high": 314.0, "frequency": 3.03, "low": 310.0, "size": 4.0}, {"high": 324.0, "frequency": 3.03, "low": 314.0, "size": 10.0}, {"high": 337.0, "frequency": 3.03, "low": 324.0, "size": 13.0}, {"high": 345.0, "frequency": 3.03, "low": 337.0, "size": 8.0}, {"high": 357.0, "frequency": 3.03, "low": 345.0, "size": 12.0}, {"high": 368.0, "frequency": 3.03, "low": 357.0, "size": 11.0}, {"high": 377.0, "frequency": 3.03, "low": 368.0, "size": 9.0}, {"high": 378.0, "frequency": 3.03, "low": 377.0, "size": 1.0}, {"high": 389.0, "frequency": 3.03, "low": 378.0, "size": 11.0}, {"high": 419.0, "frequency": 3.03, "low": 389.0, "size": 30.0}, {"high": 436.0, "frequency": 3.03, "low": 419.0, "size": 17.0}, {"high": 442.0, "frequency": 3.03, "low": 436.0, "size": 6.0}, {"high": 456.0, "frequency": 3.03, "low": 442.0, "size": 14.0}, {"high": 461.0, "frequency": 3.03, "low": 456.0, "size": 5.0}, {"high": 470.0, "frequency": 3.03, "low": 461.0, "size": 9.0}, {"high": 477.0, "frequency": 3.03, "low": 470.0, "size": 7.0}, {"high": 488.0, "frequency": 3.03, "low": 477.0, "size": 11.0}, {"high": 490.0, "frequency": 3.03, "low": 488.0, "size": 2.0}, {"high": 497.0, "frequency": 3.03, "low": 490.0, "size": 7.0}, {"high": 509.0, "frequency": 3.03, "low": 497.0, "size": 12.0}, {"high": 511.0, "frequency": 3.03, "low": 509.0, "size": 2.0}, {"high": 515.0, "frequency": 3.03, "low": 511.0, "size": 4.0}, {"high": 660.0, "frequency": 3.03, "low": 515.0, "size": 145.0}, {"high": 682.0, "frequency": 3.03, "low": 660.0, "size": 22.0}, {"high": 712.0, "frequency": 3.03, "low": 682.0, "size": 30.0}, {"high": 730.0, "frequency": 3.03, "low": 712.0, "size": 18.0}, {"high": 781.0, "frequency": 3.03, "low": 730.0, "size": 51.0}]