[{"high": 471.0, "frequency": 8489.52736318408, "low": 471.0, "ff": 5765, "vf": 2827791.466666671, "v": [2827791.466666671, 455.61912558175538, 1.0], "vv": 1605956178.4306955, "size": 0.0}, {"high": 471.0, "frequency": 1, "vv": 206116.0, "ff": 1, "v": [454.0, 454.0, 1], "size": -16.0, "vf": 454.0, "low": 454.0}, {"high": 471.0, "frequency": 1, "vv": 210222.25, "ff": 1, "v": [458.5, 458.5, 1], "size": -11.5, "vf": 458.5, "low": 458.5}, {"high": 471.0, "frequency": 1, "vv": 209153.77777777746, "ff": 1, "v": [457.333333333333, 457.333333333333, 1], "size": -12.666666666667027, "vf": 457.333333333333, "low": 457.333333333333}, {"high": 471.0, "frequency": 1, "vv": 207480.25, "ff": 1, "v": [455.5, 455.5, 1], "size": -14.5, "vf": 455.5, "low": 455.5}, {"high": 471.0, "frequency": 1, "vv": 203852.25, "ff": 1, "v": [451.5, 451.5, 1], "size": -18.5, "vf": 451.5, "low": 451.5}, {"high": 471.0, "frequency": 1, "vv": 205209.0, "ff": 1, "v": [453.0, 453.0, 1], "size": -17.0, "vf": 453.0, "low": 453.0}, {"high": 471.0, "frequency": 1, "vv": 205209.0, "ff": 1, "v": [453.0, 453.0, 1], "size": -17.0, "vf": 453.0, "low": 453.0}, {"high": 471.0, "frequency": 1, "vv": 204907.11111111144, "ff": 1, "v": [452.666666666667, 452.666666666667, 1], "size": -17.333333333332973, "vf": 452.666666666667, "low": 452.666666666667}, {"high": 471.0, "frequency": 1, "vv": 207936.0, "ff": 1, "v": [456.0, 456.0, 1], "size": -14.0, "vf": 456.0, "low": 456.0}, {"high": 471.0, "frequency": 1, "vv": 207632.11111111144, "ff": 1, "v": [455.666666666667, 455.666666666667, 1], "size": -14.333333333332973, "vf": 455.666666666667, "low": 455.666666666667}, {"high": 471.0, "frequency": 1, "vv": 205209.0, "ff": 1, "v": [453.0, 453.0, 1], "size": -17.0, "vf": 453.0, "low": 453.0}, {"high": 471.0, "frequency": 1, "vv": 205209.0, "ff": 1, "v": [453.0, 453.0, 1], "size": -17.0, "vf": 453.0, "low": 453.0}, {"high": 471.0, "frequency": 1, "vv": 204756.25, "ff": 1, "v": [452.5, 452.5, 1], "size": -17.5, "vf": 452.5, "low": 452.5}, {"high": 471.0, "frequency": 1, "vv": 202050.25, "ff": 1, "v": [449.5, 449.5, 1], "size": -20.5, "vf": 449.5, "low": 449.5}, {"high": 471.0, "frequency": 1, "vv": 205209.0, "ff": 1, "v": [453.0, 453.0, 1], "size": -17.0, "vf": 453.0, "low": 453.0}, {"high": 471.0, "frequency": 1, "vv": 207936.0, "ff": 1, "v": [456.0, 456.0, 1], "size": -14.0, "vf": 456.0, "low": 456.0}, {"high": 471.0, "frequency": 1, "vv": 204605.44444444412, "ff": 1, "v": [452.333333333333, 452.333333333333, 1], "size": -17.666666666667027, "vf": 452.333333333333, "low": 452.333333333333}, {"high": 471.0, "frequency": 1, "vv": 207480.25, "ff": 1, "v": [455.5, 455.5, 1], "size": -14.5, "vf": 455.5, "low": 455.5}, {"high": 471.0, "frequency": 1, "vv": 208240.11111111077, "ff": 1, "v": [456.333333333333, 456.333333333333, 1], "size": -13.666666666667027, "vf": 456.333333333333, "low": 456.333333333333}, {"high": 471.0, "frequency": 1, "vv": 200704.0, "ff": 1, "v": [448.0, 448.0, 1], "size": -22.0, "vf": 448.0, "low": 448.0}, {"high": 471.0, "frequency": 1, "vv": 202500.0, "ff": 1, "v": [450.0, 450.0, 1], "size": -20.0, "vf": 450.0, "low": 450.0}, {"high": 471.0, "frequency": 1, "vv": 201601.0, "ff": 1, "v": [449.0, 449.0, 1], "size": -21.0, "vf": 449.0, "low": 449.0}, {"high": 471.0, "frequency": 1, "vv": 202050.25, "ff": 1, "v": [449.5, 449.5, 1], "size": -20.5, "vf": 449.5, "low": 449.5}, {"high": 471.0, "frequency": 1, "vv": 206116.0, "ff": 1, "v": [454.0, 454.0, 1], "size": -16.0, "vf": 454.0, "low": 454.0}, {"high": 471.0, "frequency": 1, "vv": 202500.0, "ff": 1, "v": [450.0, 450.0, 1], "size": -20.0, "vf": 450.0, "low": 450.0}, {"high": 471.0, "frequency": 1, "vv": 202200.11111111144, "ff": 1, "v": [449.666666666667, 449.666666666667, 1], "size": -20.333333333332973, "vf": 449.666666666667, "low": 449.666666666667}, {"high": 471.0, "frequency": 1, "vv": 203852.25, "ff": 1, "v": [451.5, 451.5, 1], "size": -18.5, "vf": 451.5, "low": 451.5}, {"high": 471.0, "frequency": 1, "vv": 211600.0, "ff": 1, "v": [460.0, 460.0, 1], "size": -10.0, "vf": 460.0, "low": 460.0}, {"high": 471.0, "frequency": 1, "vv": 208392.25, "ff": 1, "v": [456.5, 456.5, 1], "size": -13.5, "vf": 456.5, "low": 456.5}, {"high": 471.0, "frequency": 1, "vv": 207480.25, "ff": 1, "v": [455.5, 455.5, 1], "size": -14.5, "vf": 455.5, "low": 455.5}, {"high": 471.0, "frequency": 1, "vv": 202500.0, "ff": 1, "v": [450.0, 450.0, 1], "size": -20.0, "vf": 450.0, "low": 450.0}, {"high": 471.0, "frequency": 1, "vv": 200704.0, "ff": 1, "v": [448.0, 448.0, 1], "size": -22.0, "vf": 448.0, "low": 448.0}, {"high": 471.0, "frequency": 1, "vv": 203852.25, "ff": 1, "v": [451.5, 451.5, 1], "size": -18.5, "vf": 451.5, "low": 451.5}, {"high": 471.0, "frequency": 1, "vv": 203852.25, "ff": 1, "v": [451.5, 451.5, 1], "size": -18.5, "vf": 451.5, "low": 451.5}, {"high": 471.0, "frequency": 1, "vv": 206570.25, "ff": 1, "v": [454.5, 454.5, 1], "size": -15.5, "vf": 454.5, "low": 454.5}, {"high": 471.0, "frequency": 1, "vv": 206721.7777777781, "ff": 1, "v": [454.666666666667, 454.666666666667, 1], "size": -15.333333333332973, "vf": 454.666666666667, "low": 454.666666666667}, {"high": 471.0, "frequency": 1, "vv": 203401.0, "ff": 1, "v": [451.0, 451.0, 1], "size": -19.0, "vf": 451.0, "low": 451.0}, {"high": 471.0, "frequency": 1, "vv": 203401.0, "ff": 1, "v": [451.0, 451.0, 1], "size": -19.0, "vf": 451.0, "low": 451.0}, {"high": 471.0, "frequency": 1, "vv": 207025.0, "ff": 1, "v": [455.0, 455.0, 1], "size": -15.0, "vf": 455.0, "low": 455.0}, {"high": 471.0, "frequency": 1, "vv": 209764.0, "ff": 1, "v": [458.0, 458.0, 1], "size": -12.0, "vf": 458.0, "low": 458.0}, {"high": 471.0, "frequency": 1, "vv": 211600.0, "ff": 1, "v": [460.0, 460.0, 1], "size": -10.0, "vf": 460.0, "low": 460.0}, {"high": 471.0, "frequency": 1, "vv": 208544.44444444479, "ff": 1, "v": [456.666666666667, 456.666666666667, 1], "size": -13.333333333332973, "vf": 456.666666666667, "low": 456.666666666667}, {"high": 471.0, "frequency": 1, "vv": 214369.0, "ff": 1, "v": [463.0, 463.0, 1], "size": -7.0, "vf": 463.0, "low": 463.0}, {"high": 475.25, "frequency": 1, "vv": 224913.0625, "ff": 1, "v": [474.25, 474.25, 1], "size": 4.25, "vf": 474.25, "low": 471.0}, {"high": 483.333333333333, "frequency": 2, "vv": 232645.44444444409, "ff": 1, "v": [482.333333333333, 482.333333333333, 1], "size": 8.083333333332973, "vf": 482.333333333333, "low": 475.25}, {"high": 485.5, "frequency": 7, "vv": 234740.25, "ff": 1, "v": [484.5, 484.5, 1], "size": 2.1666666666670267, "vf": 484.5, "low": 483.333333333333}, {"high": 491.333333333333, "frequency": 93, "vv": 240426.77777777743, "ff": 1, "v": [490.333333333333, 490.333333333333, 1], "size": 5.833333333332973, "vf": 490.333333333333, "low": 485.5}, {"high": 495.333333333333, "frequency": 65, "vv": 244365.44444444409, "ff": 1, "v": [494.333333333333, 494.333333333333, 1], "size": 4.0, "vf": 494.333333333333, "low": 491.333333333333}, {"high": 500.0, "frequency": 149, "vv": 249001.0, "ff": 1, "v": [499.0, 499.0, 1], "size": 4.666666666667027, "vf": 499.0, "low": 495.333333333333}, {"high": 503.5, "frequency": 270, "vv": 252506.25, "ff": 1, "v": [502.5, 502.5, 1], "size": 3.5, "vf": 502.5, "low": 500.0}, {"high": 507.666666666667, "frequency": 420, "vv": 256711.11111111147, "ff": 1, "v": [506.666666666667, 506.666666666667, 1], "size": 4.166666666667027, "vf": 506.666666666667, "low": 503.5}, {"high": 509.0, "frequency": 109, "vv": 258064.0, "ff": 1, "v": [508.0, 508.0, 1], "size": 1.3333333333329733, "vf": 508.0, "low": 507.666666666667}, {"high": 510.5, "frequency": 118, "vv": 259590.25, "ff": 1, "v": [509.5, 509.5, 1], "size": 1.5, "vf": 509.5, "low": 509.0}, {"high": 517.0, "frequency": 437, "vv": 266256.0, "ff": 1, "v": [516.0, 516.0, 1], "size": 6.5, "vf": 516.0, "low": 510.5}, {"high": 522.25, "frequency": 208, "vv": 271701.5625, "ff": 1, "v": [521.25, 521.25, 1], "size": 5.25, "vf": 521.25, "low": 517.0}, {"high": 526.75, "frequency": 121, "vv": 276413.0625, "ff": 1, "v": [525.75, 525.75, 1], "size": 4.5, "vf": 525.75, "low": 522.25}, {"high": 528.75, "frequency": 40, "vv": 278520.0625, "ff": 1, "v": [527.75, 527.75, 1], "size": 2.0, "vf": 527.75, "low": 526.75}, {"high": 535.5, "frequency": 215, "vv": 285690.25, "ff": 1, "v": [534.5, 534.5, 1], "size": 6.75, "vf": 534.5, "low": 528.75}, {"high": 569.75, "frequency": 1143, "vv": 323476.5625, "ff": 1, "v": [568.75, 568.75, 1], "size": 34.25, "vf": 568.75, "low": 535.5}, {"high": 594.75, "frequency": 826, "vv": 352539.0625, "ff": 1, "v": [593.75, 593.75, 1], "size": 25.0, "vf": 593.75, "low": 569.75}, {"high": 601.75, "frequency": 112, "vv": 360900.5625, "ff": 1, "v": [600.75, 600.75, 1], "size": 7.0, "vf": 600.75, "low": 594.75}, {"high": 624.0, "frequency": 312, "vv": 388129.0, "ff": 1, "v": [623.0, 623.0, 1], "size": 22.25, "vf": 623.0, "low": 601.75}, {"high": 632.0, "frequency": 137, "vv": 398161.0, "ff": 1, "v": [631.0, 631.0, 1], "size": 8.0, "vf": 631.0, "low": 624.0}, {"high": 637.0, "frequency": 91, "vv": 404496.0, "ff": 1, "v": [636.0, 636.0, 1], "size": 5.0, "vf": 636.0, "low": 632.0}, {"high": 664.0, "frequency": 351, "vv": 439569.0, "ff": 1, "v": [663.0, 663.0, 1], "size": 27.0, "vf": 663.0, "low": 637.0}, {"high": 666.333333333333, "frequency": 31, "vv": 442668.44444444403, "ff": 1, "v": [665.333333333333, 665.333333333333, 1], "size": 2.33333333333303, "vf": 665.333333333333, "low": 664.0}, {"high": 670.5, "frequency": 62, "vv": 448230.25, "ff": 1, "v": [669.5, 669.5, 1], "size": 4.16666666666697, "vf": 669.5, "low": 666.333333333333}, {"high": 680.25, "frequency": 138, "vv": 461380.5625, "ff": 1, "v": [679.25, 679.25, 1], "size": 9.75, "vf": 679.25, "low": 670.5}, {"high": 685.666666666667, "frequency": 56, "vv": 468768.44444444485, "ff": 1, "v": [684.666666666667, 684.666666666667, 1], "size": 5.41666666666697, "vf": 684.666666666667, "low": 680.25}, {"high": 707.25, "frequency": 160, "vv": 498789.0625, "ff": 1, "v": [706.25, 706.25, 1], "size": 21.58333333333303, "vf": 706.25, "low": 685.666666666667}, {"high": 713.625, "frequency": 146, "vv": 507834.390625, "ff": 1, "v": [712.625, 712.625, 1], "size": 6.375, "vf": 712.625, "low": 707.25}, {"high": 720.0, "frequency": 222, "vv": 516961.0, "ff": 1, "v": [719.0, 719.0, 1], "size": 6.375, "vf": 719.0, "low": 713.625}, {"high": 731.25, "frequency": 287, "vv": 533265.0625, "ff": 1, "v": [730.25, 730.25, 1], "size": 11.25, "vf": 730.25, "low": 720.0}, {"high": 740.0, "frequency": 171, "vv": 546121.0, "ff": 1, "v": [739.0, 739.0, 1], "size": 8.75, "vf": 739.0, "low": 731.25}, {"high": 757.25, "frequency": 151, "vv": 571914.0625, "ff": 1, "v": [756.25, 756.25, 1], "size": 17.25, "vf": 756.25, "low": 740.0}, {"high": 762.0, "frequency": 32, "vv": 579121.0, "ff": 1, "v": [761.0, 761.0, 1], "size": 4.75, "vf": 761.0, "low": 757.25}, {"high": 764.0, "frequency": 17, "vv": 582169.0, "ff": 1, "v": [763.0, 763.0, 1], "size": 2.0, "vf": 763.0, "low": 762.0}, {"high": 772.333333333333, "frequency": 63, "vv": 594955.11111111066, "ff": 1, "v": [771.333333333333, 771.333333333333, 1], "size": 8.33333333333303, "vf": 771.333333333333, "low": 764.0}, {"high": 781.25, "frequency": 52, "vv": 608790.0625, "ff": 1, "v": [780.25, 780.25, 1], "size": 8.91666666666697, "vf": 780.25, "low": 772.333333333333}, {"high": 788.25, "frequency": 73, "vv": 619762.5625, "ff": 1, "v": [787.25, 787.25, 1], "size": 7.0, "vf": 787.25, "low": 781.25}, {"high": 790.5, "frequency": 18, "vv": 623310.25, "ff": 1, "v": [789.5, 789.5, 1], "size": 2.25, "vf": 789.5, "low": 788.25}, {"high": 799.5, "frequency": 128, "vv": 637602.25, "ff": 1, "v": [798.5, 798.5, 1], "size": 9.0, "vf": 798.5, "low": 790.5}, {"high": 821.333333333333, "frequency": 250, "vv": 672946.77777777729, "ff": 1, "v": [820.333333333333, 820.333333333333, 1], "size": 21.83333333333303, "vf": 820.333333333333, "low": 799.5}, {"high": 1030.66666666667, "frequency": 1102, "vv": 1060213.4444444512, "ff": 1, "v": [1029.66666666667, 1029.66666666667, 1], "size": 209.3333333333369, "vf": 1029.66666666667, "low": 821.333333333333}, {"high": 1048.75, "frequency": 26, "vv": 1097780.0625, "ff": 1, "v": [1047.75, 1047.75, 1], "size": 18.083333333330074, "vf": 1047.75, "low": 1030.66666666667}, {"high": 1050.0, "frequency": 4, "vv": 1100401.0, "ff": 1, "v": [1049.0, 1049.0, 1], "size": 1.25, "vf": 1049.0, "low": 1048.75}, {"high": 1062.5, "frequency": 17, "vv": 1126782.25, "ff": 1, "v": [1061.5, 1061.5, 1], "size": 12.5, "vf": 1061.5, "low": 1050.0}, {"high": 1073.0, "frequency": 7, "vv": 1149184.0, "ff": 1, "v": [1072.0, 1072.0, 1], "size": 10.5, "vf": 1072.0, "low": 1062.5}, {"high": 1076.33333333333, "frequency": 6, "vv": 1156341.7777777708, "ff": 1, "v": [1075.33333333333, 1075.33333333333, 1], "size": 3.3333333333300743, "vf": 1075.33333333333, "low": 1073.0}, {"high": 1088.0, "frequency": 17, "vv": 1181569.0, "ff": 1, "v": [1087.0, 1087.0, 1], "size": 11.666666666669926, "vf": 1087.0, "low": 1076.33333333333}, {"high": 1092.0, "frequency": 5, "vv": 1190281.0, "ff": 1, "v": [1091.0, 1091.0, 1], "size": 4.0, "vf": 1091.0, "low": 1088.0}, {"high": 1101.0, "frequency": 13, "vv": 1210000.0, "ff": 1, "v": [1100.0, 1100.0, 1], "size": 9.0, "vf": 1100.0, "low": 1092.0}, {"high": 1108.0, "frequency": 10, "vv": 1225449.0, "ff": 1, "v": [1107.0, 1107.0, 1], "size": 7.0, "vf": 1107.0, "low": 1101.0}, {"high": 1111.0, "frequency": 4, "vv": 1232100.0, "ff": 1, "v": [1110.0, 1110.0, 1], "size": 3.0, "vf": 1110.0, "low": 1108.0}, {"high": 1761.0, "frequency": 1296, "vv": 3097600.0, "ff": 1, "v": [1760.0, 1760.0, 1], "size": 650.0, "vf": 1760.0, "low": 1111.0}, {"high": 1780.0, "frequency": 6, "vv": 3164841.0, "ff": 1, "v": [1779.0, 1779.0, 1], "size": 19.0, "vf": 1779.0, "low": 1761.0}, {"high": 1843.75, "frequency": 2, "vv": 3395727.5625, "ff": 1, "v": [1842.75, 1842.75, 1], "size": 63.75, "vf": 1842.75, "low": 1780.0}, {"high": 2073.0, "frequency": 5, "vv": 4293184.0, "ff": 1, "v": [2072.0, 2072.0, 1], "size": 229.25, "vf": 2072.0, "low": 1843.75}, {"high": 2077.5, "frequency": 1, "vv": 4311852.25, "ff": 1, "v": [2076.5, 2076.5, 1], "size": 4.5, "vf": 2076.5, "low": 2073.0}]