[{"rightcounter": 118762.5, "leftcounter": 167566.5, "high": 16.0859375, "frequency": 286329.0, "low": 0.0, "size": 16.0859375}, {"rightcounter": 135196.0, "leftcounter": 232667.0, "high": 64.34375, "frequency": 367863.0, "low": 16.0859375, "size": 48.2578125}, {"rightcounter": 84129.5, "leftcounter": 156867.5, "high": 159.921875, "frequency": 240997.0, "low": 64.34375, "size": 95.578125}, {"rightcounter": 447762.5, "leftcounter": 57048.5, "high": 255.5, "frequency": 504811.0, "low": 159.921875, "size": 95.578125}, {"rightcounter": 0.0, "leftcounter": 0.0, "high": 256.0, "frequency": 0, "low": 255.5, "size": 0.5}]